cofi/__init__.py
cofi/_base_problem.py
cofi/_exceptions.py
cofi/_inversion.py
cofi/_inversion_options.py
cofi/_version.py
cofi/version.py
cofi/tools/__init__.py
cofi/tools/_base_inference_tool.py
cofi/tools/_bayes_bay.py
cofi/tools/_cofi_border_collie_optimization.py
cofi/tools/_cofi_simple_newton.py
cofi/tools/_emcee.py
cofi/tools/_neighpy.py
cofi/tools/_neighpyI.py
cofi/tools/_neighpyII.py
cofi/tools/_pytorch_optim.py
cofi/tools/_scipy_lstsq.py
cofi/tools/_scipy_opt_lstsq.py
cofi/tools/_scipy_opt_min.py
cofi/tools/_scipy_sparse_lstsq.py
cofi/utils/__init__.py
cofi/utils/_multiple_runs.py
cofi/utils/_reg_base.py
cofi/utils/_reg_lp_norm.py
cofi/utils/_reg_model_cov.py
cofi-0.2.10.dist-info/licenses/LICENCE
cofi-0.2.10.dist-info/METADATA
cofi-0.2.10.dist-info/WHEEL
cofi-0.2.10.dist-info/top_level.txt
cofi-0.2.10.dist-info/RECORD
