Metadata-Version: 2.4
Name: cofi
Version: 0.2.10
Summary: Common Framework for Inference
Author: InLab, CoFI development team
Keywords: inversion,inference,python package,geoscience,geophysics
Classifier: Development Status :: 2 - Pre-Alpha
Classifier: Intended Audience :: Education
Classifier: Intended Audience :: Science/Research
Classifier: Programming Language :: Python
Classifier: Programming Language :: Python :: 3
Classifier: Programming Language :: Python :: 3.8
Classifier: Programming Language :: Python :: 3.9
Classifier: Programming Language :: Python :: 3.10
Classifier: Programming Language :: Python :: 3.11
Classifier: Programming Language :: Python :: Implementation :: CPython
Classifier: Topic :: Scientific/Engineering :: Physics
Classifier: License :: OSI Approved :: BSD License
Requires-Python: >=3.8
License-File: LICENCE
Requires-Dist: numpy>=1.18
Requires-Dist: scipy>=1.0.0
Requires-Dist: emcee>=3.1.5
Requires-Dist: arviz>=0.9.0
Requires-Dist: findiff>=0.7.0
Requires-Dist: torch>=1.10
Requires-Dist: bayesbay>=0.3.0
Requires-Dist: neighpy>=0.1.5
Dynamic: license-file
